{
    "id": "29599",
    "type": "inventoryitem",
    "isDynamic": true,
    "fields": {
        "costingmethoddisplay": "Average",
        "quantitypricingdiscountmatrixfields": "leveldiscount",
        "autoleadtime": "F",
        "_eml_nkey_": "5533458_SB1~34807~3~N",
        "type": "item",
        "purchaseconversionrate": "1",
        "invt_salesdesc": "ALAMBRE DE PUAS CORCEL III 300 MTS.",
        "lastpurchaseprice": "1.76",
        "pricingchange": "F",
        "cogsaccount": "792",
        "id": "29599",
        "unitswarningdisplayed": "F",
        "price1headercount": "5",
        "price1quantity3": "3",
        "totalquantityonhand": "2020.6",
        "price1quantity4": "6",
        "custitem_beex_fa_lateralidadmatriz": "",
        "costestimatetype": "AVGCOST",
        "softdescriptor": "1",
        "purchaseunit": "8",
        "entryformquerystring": "itemtype=InvtPart&e=T&id=29599",
        "futurehorizon": "30",
        "custitemid_artremt_fa02": "F",
        "version": "26",
        "islotitem": "T",
        "subsidiary": "1",
        "safetystocklevel": "79",
        "custpage_taxschedule_inline": "<script>var triggerType = \"edit\";</script><script type=\"text/javascript\" src=\"/core/media/media.nl?id=18590&c=5533458_SB1&h=s-ODxnrMeILAoQWJkCHaMaoXtw_hCfmBsn_ZFqYw6-u9tWyr&mv=kkhth77s&_xt=.js\"></script><script type=\"text/javascript\" src=\"/core/media/media.nl?id=18531&c=5533458_SB1&h=amUwTfcyLaWoOQudYKiFpd7oXwPlkiJdxTOLVogRDnowKPik&mv=kkhth1tc&_xt=.js\"></script>",
        "custitem_beex_fa_grano": "",
        "shippingcost": "0.00",
        "handlingcostunits": "per MT",
        "saleunit": "8",
        "stockunit": "8",
        "custitem22": "",
        "custitem23": "",
        "custitem20": "",
        "custitem21": "",
        "quantitypricingdiscountheadercount": "4",
        "createddate": "30/5/2020 12:45 pm",
        "isserialitem": "F",
        "custitem28": "",
        "custitem29": "",
        "custitem26": "",
        "custitemid_artnvo_fa01": "F",
        "supplyreplenishmentmethod": "REORDER_POINT",
        "incomeaccount": "790",
        "custitem27": "",
        "itemidorig": "ALAMBRE DE PUAS CORCEL III 300 MTS.",
        "custitem24": "",
        "custitem25": "",
        "nluser": "34807",
        "custitemcustomproveedorcopraart": "INDUSTRIAS EN ACERO MALLA INDE S.A.DE C.V.",
        "currency": "1",
        "origbinactive": "F",
        "usebins": "T",
        "custitem11": "",
        "invt_dispname": "ALAMBRE DE PUAS CORCEL III 300 MTS.",
        "seasonaldemand": "F",
        "enforceminqtyinternally": "T",
        "shippingcostunits": "per MT",
        "unitstypewarningdisplayed": "T",
        "custitem10": "",
        "custitem19": "0",
        "custitem17": "",
        "custitem18": "2",
        "custitem16": "1",
        "shipindividually": "F",
        "customform": "91",
        "minimumquantityunits": "MTS",
        "displayname": "ALAMBRE DE PUAS CORCEL III 300 MTS.",
        "isdropshipitem": "F",
        "nlloc": "0",
        "nlsub": "1",
        "unitstypefracconv": "F",
        "binmapchange": "F",
        "itemtypename": "Lot Numbered Inventory Item",
        "custitemcustitemcustomproveedorcopra2": "ALMAZAN ITURBE ROGELIO",
        "isonline": "T",
        "totalquantityonhandunits": "MTS",
        "autoreorderpoint": "F",
        "accchange": "F",
        "custitem_ste_taxschedule": "1",
        "custitemactualizacion_precio_hijos": "F",
        "totalvalue": "3298.75",
        "salesdescription": "ALAMBRE DE PUAS CORCEL III 300 MTS.",
        "costestimateunits": "per MT",
        "origcost": "1.58",
        "quantitypricingdiscountheader": "levelcount",
        "custitem_enviado": "F",
        "baseunit": "8",
        "weight": "0",
        "custpage_changed_nexuses": "",
        "origexchangerate": "1.00",
        "includechildren": "T",
        "custitem8": "293",
        "custitem3": "167",
        "custitem2": "3",
        "custitem_fa_lista_personalizada": "1",
        "custitem5": "20",
        "custitem1": "34",
        "matchbilltoreceipt": "F",
        "rectype_190_1052_maxnkey": "21234",
        "usemarginalrates": "F",
        "vendorname": "ALAMBRE DE PUAS CORCEL III 300 MTS.",
        "modifiableitemid": "ALAMBRE DE PUAS CORCEL III 300 MTS.",
        "origcostunits": "per MT",
        "isinactive": "F",
        "wfinstances": "",
        "purchasedescription": "ALAMBRE CORCEL ALTA TENSION: III (300 MTRS)= 431 KGS-F                CALIBRE: 15.5  CALIBRE DE PUAS: 16.5  RESISTECIA A LA RUPTURA: 454    ROLLOS POR TARIMA: 45  NUMERO DE PUNTAS POR PUA: 4                    MAYOR RESISTENCIA A LA RUPTURA Y OX",
        "exchangerate": "1",
        "maximumquantityunits": "MTS",
        "atpmethod": "CUMULATIVE_ATP_WITH_LOOK_AHEAD",
        "weightunit": "1",
        "nsapiCT": "1642726977861",
        "price1matrixfields": "price",
        "itemid": "ALAMBRE DE PUAS CORCEL III 300 MTS.",
        "sys_id": "3595132910625931",
        "offersupport": "F",
        "lastpurchasepriceunits": "per MT",
        "price1header": "price1quantity",
        "nldept": "0",
        "assetaccount": "752",
        "unitstype": "8",
        "costunits": "per MT",
        "price1quantity1": "0",
        "price1quantity2": "1",
        "tracklandedcost": "F",
        "copydescription": "F",
        "cost": "1.58",
        "templatestored": "F",
        "lastmodifieddate": "22/2/2021 6:22 pm",
        "costingmethod": "AVG",
        "weightunits": "per MT",
        "autopreferredstocklevel": "F",
        "preferredlocation": "25",
        "nlrole": "3",
        "quantityreorderunits": "Quantity On Hand, Reorder Point, Quantity On Order, and Quantity Committed are in MTS",
        "isgcocompliant": "T",
        "baserecordtype": "lotnumberedinventoryitem",
        "upccode": "ALAMPUAACEIII360",
        "averagecostunits": "per MT",
        "keywordschange": "F",
        "averagecost": "1.63",
        "hasparent": "F",
        "itemtype": "InvtPart",
        "safetystocklevelunits": "MTS",
        "saleconversionrate": "1",
        "originalusebins": "T",
        "location": "25",
        "isspecialorderitem": "F",
        "transferpriceunits": "per MT",
        "vendormapchange": "F",
        "haschildren": "F",
        "stockconversionrate": "1"
    },
    "sublists": {
        "recmachcustrecord_fa_padre": {
            "currentline": {
                "custrecord_fa_nivel_de_precio": "",
                "custrecord_fa_porcentaje": "",
                "custrecord_fa_porcentaje_escala_1": "0.0%",
                "custrecord_fa_porcentaje_escala_2": "0.0%",
                "custrecord_fa_porcentaje_escala_3": "0.0%",
                "custrecord_fa_porcentaje_escala_4": "0.0%",
                "custrecord_fa_porcentaje_escala_5": "0.0%",
                "id": "",
                "owner": "",
                "rec190view": "",
                "recordischanged": "",
                "sys_id": "-3595134819454474",
                "sys_parentid": "3595132910625931",
                "version": "",
                "#": "3"
            },
            "line 1": {
                "custrecord_fa_nivel_de_precio": "1",
                "custrecord_fa_porcentaje": null,
                "custrecord_fa_porcentaje_escala_1": "44.0%",
                "custrecord_fa_porcentaje_escala_2": "0.0%",
                "custrecord_fa_porcentaje_escala_3": "0.0%",
                "custrecord_fa_porcentaje_escala_4": "0.0%",
                "custrecord_fa_porcentaje_escala_5": "0.0%",
                "id": "1700",
                "owner": "111",
                "recordischanged": null,
                "sys_id": "3595132910692525",
                "sys_parentid": "3595132910625931",
                "version": "0"
            },
            "line 2": {
                "custrecord_fa_nivel_de_precio": "2",
                "custrecord_fa_porcentaje": null,
                "custrecord_fa_porcentaje_escala_1": "32.0%",
                "custrecord_fa_porcentaje_escala_2": "0.0%",
                "custrecord_fa_porcentaje_escala_3": "0.0%",
                "custrecord_fa_porcentaje_escala_4": "0.0%",
                "custrecord_fa_porcentaje_escala_5": "0.0%",
                "id": "11310",
                "owner": "111",
                "recordischanged": null,
                "sys_id": "3595132910672295",
                "sys_parentid": "3595132910625931",
                "version": "0"
            }
        },
        "quantitypricinglevel": {},
        "binnumber": {
            "currentline": {
                "binnumber": "",
                "isold": "",
                "location": "",
                "locationactive": "",
                "onhand": "",
                "onhandavail": "",
                "preferredbin": "",
                "sys_id": "-3595134819385985",
                "sys_parentid": "3595132910625931",
                "#": "2"
            },
            "line 1": {
                "binnumber": "1630",
                "binnumber_display": "AC/AC/P002/0000/A018",
                "isold": "T",
                "location": "25",
                "location_display": "FIGUEACERO",
                "locationactive": "Yes",
                "onhand": "2020.6",
                "onhandavail": "2020.6",
                "preferredbin": "T",
                "sys_id": "3595132910706653",
                "sys_parentid": "3595132910625931"
            }
        },
        "itemvendor": {
            "currentline": {
                "preferredvendor": "",
                "purchaseprice": "",
                "schedule": "",
                "subsidiary": "",
                "sys_id": "-3595134820205275",
                "sys_parentid": "3595132910625931",
                "vendor": "",
                "vendorcode": "",
                "vendorcurrencyid": "",
                "vendorcurrencyname": "",
                "vendorprices": "",
                "#": "3"
            },
            "line 1": {
                "preferredvendor": "T",
                "purchaseprice": null,
                "schedule": null,
                "schedule_display": null,
                "subsidiary": "1",
                "subsidiary_display": "Figueacero, SA de CV",
                "sys_id": "3595132908144689",
                "sys_parentid": "3595132910625931",
                "vendor": "23600",
                "vendor_display": "116 INGENIERIA Y PRODUCTOS DE ACERO,SA.DE CV.",
                "vendorcode": null,
                "vendorcurrencyid": "1",
                "vendorcurrencyname": "Peso Mexicano",
                "vendorprices": null
            },
            "line 2": {
                "preferredvendor": "F",
                "purchaseprice": null,
                "schedule": null,
                "schedule_display": null,
                "subsidiary": "1",
                "subsidiary_display": "Figueacero, SA de CV",
                "sys_id": "3595132908144690",
                "sys_parentid": "3595132910625931",
                "vendor": "23707",
                "vendor_display": "223 INDUSTRIAS EN ACERO MALLA INDE S.A.DE C.V.",
                "vendorcode": null,
                "vendorcurrencyid": "1",
                "vendorcurrencyname": "Peso Mexicano",
                "vendorprices": null
            }
        },
        "translations": {
            "currentline": {
                "displayname": "",
                "language": "",
                "locale": "",
                "salesdescription": "",
                "sys_id": "-3595134820257357",
                "sys_parentid": "3595132910625931",
                "#": "3"
            },
            "line 1": {
                "displayname": null,
                "language": "Latin American Spanish",
                "locale": "es_AR",
                "salesdescription": null,
                "sys_id": "3595132910762545",
                "sys_parentid": "3595132910625931"
            },
            "line 2": {
                "displayname": null,
                "language": "English (U.S.)",
                "locale": "en_US",
                "salesdescription": null,
                "sys_id": "3595132910753487",
                "sys_parentid": "3595132910625931"
            }
        },
        "hierarchyversions": {},
        "quantitypricingdiscount": {
            "line 1": {
                "leveldiscount[1]": null,
                "leveldiscount[2]": null,
                "leveldiscount[3]": null,
                "leveldiscount[4]": null,
                "levelpricename": "Menudeo",
                "levelpricetype": "1",
                "sys_id": "3595132910862689",
                "sys_parentid": "3595132910625931"
            },
            "line 2": {
                "leveldiscount[1]": null,
                "leveldiscount[2]": null,
                "leveldiscount[3]": null,
                "leveldiscount[4]": null,
                "levelpricename": "Figueacero_prueba",
                "levelpricetype": "20",
                "sys_id": "3595132910853289",
                "sys_parentid": "3595132910625931"
            },
            "line 3": {
                "leveldiscount[1]": null,
                "leveldiscount[2]": null,
                "leveldiscount[3]": null,
                "leveldiscount[4]": null,
                "levelpricename": "MENUDEO A FERRETERÍA",
                "levelpricetype": "6",
                "sys_id": "3595132910843886",
                "sys_parentid": "3595132910625931"
            },
            "line 4": {
                "leveldiscount[1]": null,
                "leveldiscount[2]": null,
                "leveldiscount[3]": null,
                "leveldiscount[4]": null,
                "levelpricename": "Mayoreo",
                "levelpricetype": "2",
                "sys_id": "3595132910834178",
                "sys_parentid": "3595132910625931"
            },
            "line 5": {
                "leveldiscount[1]": null,
                "leveldiscount[2]": null,
                "leveldiscount[3]": null,
                "leveldiscount[4]": null,
                "levelpricename": "Menudeo",
                "levelpricetype": "16",
                "sys_id": "3595132910824711",
                "sys_parentid": "3595132910625931"
            },
            "line 6": {
                "leveldiscount[1]": null,
                "leveldiscount[2]": null,
                "leveldiscount[3]": null,
                "leveldiscount[4]": null,
                "levelpricename": "Precio alternativo 3",
                "levelpricetype": "4",
                "sys_id": "3595132910815229",
                "sys_parentid": "3595132910625931"
            },
            "line 7": {
                "leveldiscount[1]": null,
                "leveldiscount[2]": null,
                "leveldiscount[3]": null,
                "leveldiscount[4]": null,
                "levelpricename": "Promedio",
                "levelpricetype": "14",
                "sys_id": "3595132910805597",
                "sys_parentid": "3595132910625931"
            },
            "line 8": {
                "leveldiscount[1]": null,
                "leveldiscount[2]": null,
                "leveldiscount[3]": null,
                "leveldiscount[4]": null,
                "levelpricename": "SEMI MAYOREO",
                "levelpricetype": "19",
                "sys_id": "3595132910796057",
                "sys_parentid": "3595132910625931"
            },
            "line 9": {
                "leveldiscount[1]": null,
                "leveldiscount[2]": null,
                "leveldiscount[3]": null,
                "leveldiscount[4]": null,
                "levelpricename": "super mayoreo",
                "levelpricetype": "3",
                "sys_id": "3595132910786567",
                "sys_parentid": "3595132910625931"
            },
            "line 10": {
                "leveldiscount[1]": null,
                "leveldiscount[2]": null,
                "leveldiscount[3]": null,
                "leveldiscount[4]": null,
                "levelpricename": "FERRETERÍA",
                "levelpricetype": "5",
                "sys_id": "3595132910774898",
                "sys_parentid": "3595132910625931"
            }
        },
        "price1": {
            "line 1": {
                "currency": "1",
                "discount": null,
                "discountdisplay": null,
                "price[1]": "4.02",
                "price[2]": "3.93",
                "price[3]": "3.79",
                "price[4]": "3.68",
                "price[5]": null,
                "pricelevel": "1",
                "pricelevelname": "Menudeo",
                "sys_id": "3595132910983075",
                "sys_parentid": "3595132910625931"
            },
            "line 2": {
                "currency": "1",
                "discount": null,
                "discountdisplay": null,
                "price[1]": null,
                "price[2]": null,
                "price[3]": null,
                "price[4]": null,
                "price[5]": null,
                "pricelevel": "20",
                "pricelevelname": "Figueacero_prueba",
                "sys_id": "3595132910971788",
                "sys_parentid": "3595132910625931"
            },
            "line 3": {
                "currency": "1",
                "discount": null,
                "discountdisplay": null,
                "price[1]": null,
                "price[2]": null,
                "price[3]": null,
                "price[4]": null,
                "price[5]": null,
                "pricelevel": "6",
                "pricelevelname": "MENUDEO A FERRETERÍA",
                "sys_id": "3595132910960390",
                "sys_parentid": "3595132910625931"
            },
            "line 4": {
                "currency": "1",
                "discount": null,
                "discountdisplay": null,
                "price[1]": null,
                "price[2]": null,
                "price[3]": null,
                "price[4]": null,
                "price[5]": null,
                "pricelevel": "2",
                "pricelevelname": "Mayoreo",
                "sys_id": "3595132910949066",
                "sys_parentid": "3595132910625931"
            },
            "line 5": {
                "currency": "1",
                "discount": null,
                "discountdisplay": null,
                "price[1]": null,
                "price[2]": null,
                "price[3]": null,
                "price[4]": null,
                "price[5]": null,
                "pricelevel": "16",
                "pricelevelname": "Menudeo",
                "sys_id": "3595132910937488",
                "sys_parentid": "3595132910625931"
            },
            "line 6": {
                "currency": "1",
                "discount": null,
                "discountdisplay": null,
                "price[1]": null,
                "price[2]": null,
                "price[3]": null,
                "price[4]": null,
                "price[5]": null,
                "pricelevel": "4",
                "pricelevelname": "Precio alternativo 3",
                "sys_id": "3595132910926015",
                "sys_parentid": "3595132910625931"
            },
            "line 7": {
                "currency": "1",
                "discount": null,
                "discountdisplay": null,
                "price[1]": null,
                "price[2]": null,
                "price[3]": null,
                "price[4]": null,
                "price[5]": null,
                "pricelevel": "14",
                "pricelevelname": "Promedio",
                "sys_id": "3595132910914501",
                "sys_parentid": "3595132910625931"
            },
            "line 8": {
                "currency": "1",
                "discount": null,
                "discountdisplay": null,
                "price[1]": null,
                "price[2]": null,
                "price[3]": null,
                "price[4]": null,
                "price[5]": null,
                "pricelevel": "19",
                "pricelevelname": "SEMI MAYOREO",
                "sys_id": "3595132910903056",
                "sys_parentid": "3595132910625931"
            },
            "line 9": {
                "currency": "1",
                "discount": null,
                "discountdisplay": null,
                "price[1]": null,
                "price[2]": null,
                "price[3]": null,
                "price[4]": null,
                "price[5]": null,
                "pricelevel": "3",
                "pricelevelname": "super mayoreo",
                "sys_id": "3595132910891525",
                "sys_parentid": "3595132910625931"
            },
            "line 10": {
                "currency": "1",
                "discount": null,
                "discountdisplay": null,
                "price[1]": null,
                "price[2]": null,
                "price[3]": null,
                "price[4]": null,
                "price[5]": null,
                "pricelevel": "5",
                "pricelevelname": "FERRETERÍA",
                "sys_id": "3595132910875422",
                "sys_parentid": "3595132910625931"
            }
        }
    }
}